aioaria2/__init__.py
aioaria2/client.py
aioaria2/exceptions.py
aioaria2/parser.py
aioaria2/py.typed
aioaria2/server.py
aioaria2/typing.py
aioaria2/utils.py
aioaria2-1.3.6.dist-info/LICENSE
aioaria2-1.3.6.dist-info/METADATA
aioaria2-1.3.6.dist-info/WHEEL
aioaria2-1.3.6.dist-info/top_level.txt
aioaria2-1.3.6.dist-info/RECORD
