Metadata-Version: 2.1
Name: aioaria2
Version: 1.3.6
Summary: Support Aria2 rpc client and manage server with async/await
Home-page: https://github.com/synodriver/aioaria2
Author: synodriver
Author-email: diguohuangjiajinweijun@gmail.com
Maintainer: v-vinson
License: GPLv3
Project-URL: Bug Tracker, https://github.com/synodriver/aioaria2/issues
Keywords: asyncio,Aria2
Classifier: Development Status :: 3 - Alpha
Classifier: Framework :: AsyncIO
Classifier: Operating System :: OS Independent
Classifier: License :: OSI Approved :: GNU General Public License v3 (GPLv3)
Classifier: Programming Language :: Python
Classifier: Programming Language :: Python :: 3.8
Classifier: Programming Language :: Python :: 3.9
Classifier: Programming Language :: Python :: 3.10
Classifier: Programming Language :: Python :: 3.11
Classifier: Programming Language :: Python :: 3.12
Classifier: Programming Language :: Python :: 3.13
Classifier: Programming Language :: Python :: Implementation :: CPython
Requires-Python: >=3.6
License-File: LICENSE
Requires-Dist: aiohttp
Requires-Dist: aiofiles
Requires-Dist: typing-extensions
